py21cmemu/__init__.py
py21cmemu/config.py
py21cmemu/emulator.py
py21cmemu/emulator_constants.npz
py21cmemu/get_emulator.py
py21cmemu/inputs.py
py21cmemu/models/radio_background/median_test_errors.npz
py21cmemu/models/radio_background/model.py
py21cmemu/models/radio_background/radio_background_emu_csts.npz
py21cmemu/models/radio_background/Radio_Background_Emu_Weights
py21cmemu/outputs.py
py21cmemu/properties.py
py21cmemu-2.0.0.dist-info/AUTHORS.rst
py21cmemu-2.0.0.dist-info/entry_points.txt
py21cmemu-2.0.0.dist-info/LICENSE
py21cmemu-2.0.0.dist-info/METADATA
py21cmemu-2.0.0.dist-info/WHEEL
py21cmemu-2.0.0.dist-info/RECORD
