Metadata-Version: 2.1
Name: py21cmEMU
Version: 2.0.0
Summary: Emulator of 21cmFAST summaries.
Home-page: https://github.com/21cmFAST/21cmEMU
License: MIT
Keywords: Epoch of Reionization,Cosmology
Author: Daniela Breitman
Author-email: daniela.breitman@sns.it
Requires-Python: >=3.8,<3.12
Classifier: Development Status :: 5 - Production/Stable
Classifier: License :: OSI Approved :: MIT License
Classifier: Operating System :: POSIX
Classifier: Operating System :: Unix
Classifier: Programming Language :: Python
Classifier: Programming Language :: Python :: 3
Classifier: Programming Language :: Python :: 3.8
Classifier: Programming Language :: Python :: 3.9
Classifier: Programming Language :: Python :: 3.10
Classifier: Programming Language :: Python :: 3.11
Classifier: Programming Language :: Python :: 3.7
Requires-Dist: GitPython (>=3.1.31,<4.0.0)
Requires-Dist: appdirs (>=1.4.4,<2.0.0)
Requires-Dist: click (>=8.0.1)
Requires-Dist: numpy (>=1.22.0,<2.0.0)
Requires-Dist: scipy (>=1.10.1,<2.0.0)
Requires-Dist: tensorflow (>=2.4.0,<=2.14.0)
Requires-Dist: toml (>=0.10.2,<0.11.0)
Requires-Dist: torch (>=1.9.0)
Project-URL: Changelog, https://github.com/21cmFAST/21cmEMU/releases
Project-URL: Documentation, https://21cmEMU.readthedocs.io
Project-URL: Repository, https://github.com/21cmFAST/21cmEMU
